README.md
setup.py
neohub/__init__.py
neohub/neohub.py
neohub.egg-info/PKG-INFO
neohub.egg-info/SOURCES.txt
neohub.egg-info/dependency_links.txt
neohub.egg-info/requires.txt
neohub.egg-info/top_level.txt