Metadata-Version: 2.1
Name: neohub
Version: 0.1.0
Summary: Control Neohub supported thermostats
Home-page: https://github.com/kost/neohub-python
Author: Vlatko Kosturjak
Author-email: vlatko.kosturjak@gmail.com
License: UNKNOWN
Platform: UNKNOWN
Classifier: Programming Language :: Python :: 2
Classifier: Programming Language :: Python :: 3
Classifier: License :: OSI Approved :: MIT License
Classifier: Operating System :: OS Independent
